{
  "tags": [
    {
      "name": "release",
      "version": "1.2.0",
      "commit": "7ba43f3",
      "upstream": "Releases",
      "lastUpdated": "2021-06-16T02:08:29.927Z"
    },
    {
      "name": "testing",
      "version": "",
      "commit": "",
      "upstream": "",
      "lastUpdated": ""
    },
    {
      "name": "nightly",
      "version": "89a4af1c2dc34fb0509a397cee5476b3eb8ff6e8",
      "commit": "bf61197",
      "upstream": "Every commit to master",
      "lastUpdated": "2021-06-16T02:09:09.396Z"
    }
  ],
  "pulls": 370387,
  "stars": 2
}
